sklearn_som/__init__.py
sklearn_som/som.py
sklearn_som-1.1.0.dist-info/LICENSE
sklearn_som-1.1.0.dist-info/METADATA
sklearn_som-1.1.0.dist-info/WHEEL
sklearn_som-1.1.0.dist-info/top_level.txt
sklearn_som-1.1.0.dist-info/RECORD
