Metadata-Version: 2.1
Name: sklearn-som
Version: 1.1.0
Summary: A simple planar self organizing map
Home-page: https://github.com/rileypsmith/sklearn-som
Author: Riley Smith
Author-email: 
License: MIT
Platform: UNKNOWN
Classifier: License :: OSI Approved :: MIT License
Classifier: Programming Language :: Python :: 3
Classifier: Programming Language :: Python :: 3.7
Requires-Dist: numpy
